purepythonmilter/__init__.py
purepythonmilter/_version.py
purepythonmilter/api/__init__.py
purepythonmilter/api/application.py
purepythonmilter/api/interfaces.py
purepythonmilter/api/logger.py
purepythonmilter/api/models.py
purepythonmilter/examples/__init__.py
purepythonmilter/examples/append_header_ip/__init__.py
purepythonmilter/examples/append_header_ip/__main__.py
purepythonmilter/examples/change_body/__init__.py
purepythonmilter/examples/change_body/__main__.py
purepythonmilter/examples/debug_log_all/__init__.py
purepythonmilter/examples/debug_log_all/__main__.py
purepythonmilter/protocol/__init__.py
purepythonmilter/protocol/commands.py
purepythonmilter/protocol/definitions.py
purepythonmilter/protocol/exceptions.py
purepythonmilter/protocol/packet.py
purepythonmilter/protocol/payload.py
purepythonmilter/protocol/responses.py
purepythonmilter/server/__init__.py
purepythonmilter/server/connectionhandler.py
purepythonmilter/server/milterserver.py
purepythonmilter/server/session.py
purepythonmilter-0.0.1.dist-info/Apache-2.0.txt
purepythonmilter-0.0.1.dist-info/CC0-1.0.txt
purepythonmilter-0.0.1.dist-info/METADATA
purepythonmilter-0.0.1.dist-info/WHEEL
purepythonmilter-0.0.1.dist-info/top_level.txt
purepythonmilter-0.0.1.dist-info/RECORD
