Metadata-Version: 2.1
Name: purepythonmilter
Version: 0.0.1
Summary: A Milter library and app framework in pure-Python with asyncio
Author-email: Gert van Dijk <github@gertvandijk.nl>
License: Apache License 2.0
Project-URL: homepage, https://github.com/gertvdijk/purepythonmilter
Project-URL: repository, https://github.com/gertvdijk/purepythonmilter.git
Classifier: Development Status :: 3 - Alpha
Classifier: License :: OSI Approved :: Apache Software License
Classifier: Programming Language :: Python :: 3
Classifier: Programming Language :: Python :: 3.10
Classifier: Topic :: Communications :: Email
Classifier: Topic :: Communications :: Email :: Filters
Classifier: Topic :: Communications :: Email :: Mail Transport Agents
Classifier: Topic :: Software Development :: Libraries
Classifier: Typing :: Typed
Requires-Python: >=3.10
License-File: LICENSES/Apache-2.0.txt
License-File: LICENSES/CC0-1.0.txt
Requires-Dist: attrs
Provides-Extra: development
Requires-Dist: black ; extra == 'development'
Requires-Dist: build ; extra == 'development'
Requires-Dist: flake8 ; extra == 'development'
Requires-Dist: isort ; extra == 'development'
Requires-Dist: mypy ; extra == 'development'
Requires-Dist: pytest-asyncio ; extra == 'development'
Requires-Dist: pytest-cov ; extra == 'development'
Requires-Dist: pytest ; extra == 'development'
Requires-Dist: pyupgrade ; extra == 'development'
Requires-Dist: reuse ; extra == 'development'
Requires-Dist: ruff ; extra == 'development'
Requires-Dist: setuptools-scm[toml] (>=6.2) ; extra == 'development'
Requires-Dist: twine ; extra == 'development'
Requires-Dist: validate-pyproject[all] ; extra == 'development'
Provides-Extra: examples
Requires-Dist: click ; extra == 'examples'
